rust.cpython-312-x86_64-linux-musl.so
logprep/__init__.py
logprep/configuration.py
logprep/factory.py
logprep/factory_error.py
logprep/registry.py
logprep/run_logprep.py
logprep/run_ng.py
logprep/runner.py
logprep/abc/__init__.py
logprep/abc/component.py
logprep/abc/connector.py
logprep/abc/exceptions.py
logprep/abc/getter.py
logprep/abc/input.py
logprep/abc/output.py
logprep/abc/processor.py
logprep/connector/__init__.py
logprep/connector/confluent_kafka/__init__.py
logprep/connector/confluent_kafka/input.py
logprep/connector/confluent_kafka/output.py
logprep/connector/console/__init__.py
logprep/connector/console/output.py
logprep/connector/dummy/__init__.py
logprep/connector/dummy/input.py
logprep/connector/dummy/output.py
logprep/connector/file/__init__.py
logprep/connector/file/input.py
logprep/connector/http/__init__.py
logprep/connector/http/input.py
logprep/connector/http/output.py
logprep/connector/json/__init__.py
logprep/connector/json/input.py
logprep/connector/jsonl/__init__.py
logprep/connector/jsonl/input.py
logprep/connector/jsonl/output.py
logprep/connector/opensearch/__init__.py
logprep/connector/opensearch/output.py
logprep/connector/s3/__init__.py
logprep/connector/s3/output.py
logprep/filter/__init__.py
logprep/filter/lucene_filter.py
logprep/filter/expression/__init__.py
logprep/filter/expression/filter_expression.py
logprep/framework/__init__.py
logprep/framework/pipeline.py
logprep/framework/pipeline_manager.py
logprep/framework/rule_tree/__init__.py
logprep/framework/rule_tree/demorgan_resolver.py
logprep/framework/rule_tree/node.py
logprep/framework/rule_tree/rule_parser.py
logprep/framework/rule_tree/rule_segmenter.py
logprep/framework/rule_tree/rule_sorter.py
logprep/framework/rule_tree/rule_tagger.py
logprep/framework/rule_tree/rule_tree.py
logprep/generator/__init__.py
logprep/generator/batcher.py
logprep/generator/controller.py
logprep/generator/factory.py
logprep-18.0.1.dist-info/METADATA
logprep-18.0.1.dist-info/WHEEL
logprep-18.0.1.dist-info/entry_points.txt
logprep-18.0.1.dist-info/top_level.txt
logprep-18.0.1.dist-info/RECORD
logprep-18.0.1.dist-info/licenses/LICENSE
logprep-18.0.1.dist-info/sboms/auditwheel.cdx.json
