Metadata-Version: 2.4
Name: logprep
Version: 18.0.1
Summary: Logprep allows to collect, process and forward log messages from various data sources.
License:                   GNU LESSER GENERAL PUBLIC LICENSE
Project-URL: Homepage, https://github.com/fkie-cad/Logprep
Project-URL: Documentation, https://logprep.readthedocs.io/en/latest/
Project-URL: Repository, https://github.com/fkie-cad/Logprep
Project-URL: Issues, https://github.com/fkie-cad/Logprep/issues
Project-URL: Changelog, https://github.com/fkie-cad/Logprep/blob/main/CHANGELOG.md
Keywords: kafka,etl,sre,preprocessing,opensearch,soar,logdata
Classifier: Development Status :: 3 - Alpha
Classifier: Intended Audience :: Information Technology
Classifier: License :: OSI Approved :: GNU Lesser General Public License v2 or later (LGPLv2+)
Classifier: Programming Language :: Python
Classifier: Programming Language :: Python :: 3
Classifier: Programming Language :: Python :: 3.11
Classifier: Programming Language :: Python :: 3.12
Classifier: Programming Language :: Python :: 3.13
Classifier: Programming Language :: Python :: 3.14
Classifier: Operating System :: POSIX :: Linux
Classifier: Topic :: Security
Classifier: Topic :: System :: Logging
Requires-Python: >=3.11
License-File: LICENSE
Requires-Dist: aiohttp>=3.9.2
Requires-Dist: attrs
Requires-Dist: certifi>=2023.7.22
Requires-Dist: confluent-kafka>2
Requires-Dist: filelock
Requires-Dist: geoip2
Requires-Dist: jsonref
Requires-Dist: luqum
Requires-Dist: more-itertools==8.10.0
Requires-Dist: numpy>=1.26.0
Requires-Dist: opensearch-py
Requires-Dist: prometheus_client
Requires-Dist: protobuf>=3.20.2
Requires-Dist: pycryptodome
Requires-Dist: pyparsing
Requires-Dist: scikit-learn>=1.2.0
Requires-Dist: scipy>=1.9.2
Requires-Dist: joblib
Requires-Dist: pyyaml
Requires-Dist: requests>=2.31.0
Requires-Dist: ruamel.yaml
Requires-Dist: schedule
Requires-Dist: urllib3>=1.26.17
Requires-Dist: uvicorn
Requires-Dist: deepdiff
Requires-Dist: msgspec
Requires-Dist: boto3
Requires-Dist: pydantic
Requires-Dist: click
Requires-Dist: pandas
Requires-Dist: tabulate
Requires-Dist: falcon>=3.1.3
Requires-Dist: uvloop
Requires-Dist: httptools
Provides-Extra: dev
Requires-Dist: black>=26.0.0; extra == "dev"
Requires-Dist: httpx; extra == "dev"
Requires-Dist: isort; extra == "dev"
Requires-Dist: pylint; extra == "dev"
Requires-Dist: pytest; extra == "dev"
Requires-Dist: pytest-cov; extra == "dev"
Requires-Dist: responses; extra == "dev"
Requires-Dist: jinja2; extra == "dev"
Requires-Dist: maturin; extra == "dev"
Requires-Dist: cibuildwheel; extra == "dev"
Requires-Dist: asgiref; extra == "dev"
Requires-Dist: pytest-asyncio; extra == "dev"
Requires-Dist: pre-commit; extra == "dev"
Requires-Dist: mypy>=1.18.2; extra == "dev"
Requires-Dist: psutil; extra == "dev"
Requires-Dist: types-requests; extra == "dev"
Requires-Dist: types-psutil; extra == "dev"
Requires-Dist: types-PyYaml; extra == "dev"
Provides-Extra: doc
Requires-Dist: sphinx>=8.2.0; extra == "doc"
Requires-Dist: sphinx_rtd_theme; extra == "doc"
Requires-Dist: sphinxcontrib.datatemplates; extra == "doc"
Requires-Dist: sphinxcontrib-mermaid; extra == "doc"
Requires-Dist: sphinx-copybutton; extra == "doc"
Requires-Dist: nbsphinx>=0.9; extra == "doc"
Requires-Dist: ipython>=8.7; extra == "doc"
Requires-Dist: openpyxl; extra == "doc"
Dynamic: license-file
